[
  {
    "wall_time": 1489715207.593146,
    "step": 0,
    "text": "<p><em>Italics1</em> <em>Italics2</em> <strong>bold1</strong> <strong>bold2</strong></p>"
  },
  {
    "wall_time": 1489715207.593801,
    "step": 1,
    "text": "<ol>\n<li>List item one.</li>\n<li>List item two.</li>\n<li>Sublist</li>\n<li>Sublist2</li>\n<li>List continues.</li>\n</ol>"
  },
  {
    "wall_time": 1489715207.594842,
    "step": 2,
    "text": "<table>\n<thead>\n<tr>\n<th>An</th>\n<th>Example</th>\n<th>Table</th>\n</tr>\n</thead>\n<tbody>\n<tr>\n<td>A</td>\n<td>B</td>\n<td>C</td>\n</tr>\n<tr>\n<td>1</td>\n<td>2</td>\n<td>3</td>\n</tr>\n</tbody>\n</table>"
  },
  {
    "wall_time": 1489715207.595761,
    "step": 3,
    "text": "<p>hello <a><em>you</em></a></p>"
  },
  {
    "wall_time": 1489715207.595761,
    "step": 4,
    "text": "<p><a href=\"http://tensorflow.org\">TensorFlow</a></p>"
  },
  {
    "wall_time": 1489715207.595761,
    "step": 530234352,
    "text": "&lt;script&gt;alert('xss')&lt;/script&gt;"
  }
]
